{
  "running_header": "文化取向的宣教 國度視野的牧養",
  "section_marker": "",
  "eyebrow": "",
  "title": "",
  "subtitle_en": "",
  "author": "",
  "date_line": "",
  "scripture_ref": "",
  "columns": 2,
  "blocks": [
    {
      "type": "paragraph",
      "text": "要盡心、盡性、盡意愛主你的如同自己。」這條誡命，應該著重的"
    },
    {
      "type": "paragraph",
      "text": "上帝；又要愛鄰舍如同自己。」律法是「愛」，而不是「鄰舍」。因為重要的"
    },
    {
      "type": "paragraph",
      "text": "師要顯明自己有理，又問耶穌說：「誰是「愛」，而不是誰是鄰舍。人如果"
    },
    {
      "type": "paragraph",
      "text": "是我的鄰舍呢？」耶穌就敘述好撒瑪利亞人，就會知道誰是需要他幫助的，"
    },
    {
      "type": "paragraph",
      "text": "利亞人的故事，說完了，又問那位律就會知道誰是他的鄰舍，他也就會知道"
    },
    {
      "type": "paragraph",
      "text": "法師：「你這這三個人（祭司、利未人、不是最要緊的，那麼什麼才是最重要"
    },
    {
      "type": "paragraph",
      "text": "撒瑪利亞人）哪一個是落在強盜手中 的呢？就是律法師最初提問的「承受"
    },
    {
      "type": "paragraph",
      "text": "的鄰舍呢？」律法師回答說：「是憐憫 永生」的問題。"
    },
    {
      "type": "paragraph",
      "text": "他的。」耶穌就說：「你照樣去行吧！」"
    },
    {
      "type": "paragraph",
      "text": "耶穌為什麼問有關學問的律法師這麼簡 耶穌強調的是因信心能得永生，"
    },
    {
      "type": "paragraph",
      "text": "單的問題呢？祂問的豈不是小學生閱 而不是靠行為稱義。強烈的對比告訴"
    },
    {
      "type": "paragraph",
      "text": "讀測試的問題嗎？其實耶穌要問的 發問的律法師，也在對今天的我們說"
    },
    {
      "type": "paragraph",
      "text": "問題除了「誰是我的鄰舍？」之外， 話：憑著一無所有的自己，我們做不"
    },
    {
      "type": "paragraph",
      "text": "祂也針對了「如何承受永生？」提出 到上帝要求的愛人的標準，唯有先忘"
    },
    {
      "type": "paragraph",
      "text": "振聾發聵的生命問題。 記自己、除掉驕傲，專心倚靠上帝的"
    },
    {
      "type": "paragraph",
      "text": "恩典和力量。真正體會了祂豐盛的"
    },
    {
      "type": "paragraph",
      "text": "耶穌在反問律法師「誰是我的鄰 愛，我們才能甘心樂意地付出自。同時，"
    },
    {
      "type": "paragraph",
      "text": "舍呢？」的問題的答案，是顯而易見 光是知道上帝的律法、明白自己的責"
    },
    {
      "type": "paragraph",
      "text": "的——那位以憐憫、仁慈對待受害人 任，是 فإن；祭司和利未人難道懂"
    },
    {
      "type": "paragraph",
      "text": "的撒瑪利亞人。既然答案這樣容易， 得 فإن多嗎？"
    },
    {
      "type": "paragraph",
      "text": "耶穌的反問就點出了一個含義：「誰"
    },
    {
      "type": "paragraph",
      "text": "是我的鄰舍呢？」是問錯了問題，因 這樣看來，我們非但可能不是撒"
    },
    {
      "type": "paragraph",
      "text": "為先界定愛的對象才去愛他，是不對 瑪利亞人，連祭司和利未人也做不"
    },
    {
      "type": "paragraph",
      "text": "的。耶穌以猶太人世仇的撒瑪利亞人 到；我們充其量不過是那個躺在路"
    },
    {
      "type": "paragraph",
      "text": "為例，尤其對猶太人來說，是非常難 邊、什麼也不能做、「落在強盜手中，"
    },
    {
      "type": "paragraph",
      "text": "接受的。他們素不往來、鄙視輕看的 被剝去衣裳、打個半死」的人啊！"
    },
    {
      "type": "paragraph",
      "text": "撒瑪利亞人竟然願意施救，而素來深"
    },
    {
      "type": "paragraph",
      "text": "受猶太人民景仰的、有學問、有地位 永生之道"
    },
    {
      "type": "paragraph",
      "text": "的祭司和利未人反而什麼也沒做，拍"
    },
    {
      "type": "paragraph",
      "text": "屁股就走了！由此可見，作鄰舍的 「好撒瑪利亞人」的比喻，讓"
    },
    {
      "type": "paragraph",
      "text": "事實本身並不能產生愛的行動；唯有 們看清自己，是躺在那條通往利"
    },
    {
      "type": "paragraph",
      "text": "愛才能產生愛鄰舍的行動。因此，不 路上旳可憐蟲，什麼也不能做、什麼"
    },
    {
      "type": "paragraph",
      "text": "應該問「誰是我的鄰舍呢？」而要問： 能力也沒有。耶穌所說的、也是律法"
    },
    {
      "type": "paragraph",
      "text": "「我可以成為誰的鄰舍呢？」再串連 師熟知的愛上帝、愛人的最大誡命—"
    },
    {
      "type": "paragraph",
      "text": "到之前耶穌回答的問題：「又要愛鄰舍 —就是通往永生的道路，那樣無私"
    }
  ]
}