{"date": "2009-04-19", "service": "午堂", "season": "復活期第二主日", "date_text": "主後二○○九年四月十九日", "color": "白", "preacher": "龐君華牧師", "presider": "龐君華牧師", "sermon_title": "光明的團契", "roles": {"主禮": "龐君華牧師", "證道": "龐君華牧師", "司會": "黃于庭女士", "司獻": "徐瑋良先生", "招待": "徐瑋良先生", "司琴": "劉芳良女士"}, "scriptures": ["使徒行傳4:32-35", "約翰壹書1:1-2", "約翰福音 20:19-31", "約翰福音20:19", "約翰壹書 3:1-7", "約翰福音24:36"], "hymns": [{"book": "新普頌", "no": "274", "title": "永活基督"}, {"book": "新普頌", "no": "683", "title": "求賜智勇"}], "full_text": "中華基督教衛理公會城中牧區午堂崇拜\n復活期第二主日\n主後二○○九年四月十九日\n主禮/證道：龐君華牧師\n司會： 黃于庭女士\n司獻/招待：徐瑋良先生\n司琴： 劉芳良女士\n白色象徵純潔、喜樂和真理的光輝，用於與主基督直接有關的節期，如聖誕期、\n復活期、顯現日、升天日、聖三一主日、基督登山變容主日。\n***崇拜進行時，請暫時關閉您身上的行動電話及呼叫器***\n預    備    禮\n（朝見上主的準備）\n會前音樂          隆馬欽 Gavrül Lomakin (1812-1885)\n我們讚美你Tebe Poem (Te Cantamus)\n序    樂 \t…………………………………………………………………司      琴\n宣    召    ……………………………………………………………. 司      會\n要像新生的嬰兒，時時渴慕那純淨的靈奶，好藉著它長大，得救。\n（彼得前書2:2現代中文譯本）\n頌    讚    新普頌274「永活基督」……………..………..………司會/眾立同頌\n始 禮 文\n啟：讚美我們的上主！讚美祂透過耶穌基督所彰顯的大能！\n應：讚美祂釋放了我們罪的綑綁！\n啟：讚美我們的上主！讚美祂透過耶穌基督所彰顯的大能！\n應：讚美祂衝破了死亡對我們的拘禁！\n啟：讚美我們的上主！讚美祂透過耶穌基督所彰顯的大能！\n應：讚美祂啟發了我們愛的力量！\n合：我們要加入上主的團契，一同讚美復活的基督是我們的主！\n懺      悔      禮\n心中潔淨文\t\t…………………………………………………………………（司   會）\n全能的上主，所有人的心，在主面前都無不顯明。\n心裡所羨慕的主都知道，心裡所隱藏的，也瞞不過主。\n求主用聖靈感化，潔淨我們內心的意念，使我們盡心愛主，\n恭敬歸榮耀於主的聖名。這都是靠著我們的主耶穌基督。阿們。\n召   喚\t「弟兄姊妹！請我們安靜自己的心，誠實省察自己對上主、\n對人是否盡了當盡的本分！」\n靜   默\n﹝詩歌回應﹞求主憐憫詞                                        會眾坐唱\n６１３３│３２ １２３－│３５ ５ ６５６│\n求主憐憫  我　　　 們；　求基 督 憐  憫\n２１２－│６１３２│７　５６－│\n我　們；  求主憐憫  我    們。\n認罪文\t\t…………………………………………………………………（會   眾）\n啟：我說我要向上主承認我的過犯；\n應：「全能最慈悲的天父，\n我們都走錯了路，\n離開祢的正道，如同失羣的羊。\n我們過於隨從自己心中的意思，干犯了祢的聖律。\n當作的不作，不當作的倒作。\n主阿！求祢發慈悲憐憫我們。\n凡認罪的，求祢赦免。\n悔罪的，求祢收回。\n照祢藉著我主耶穌基督，向世人宣怖的應許，\n使痛悔的人得著祢的安慰。\n又求最慈悲的父，因基督的緣故，\n幫助我們，此後為人虔誠，正直，莊重，謙恭，\n歸榮與祢的聖名。阿們。\n安慰文\t\t…………………………………………………………（主   禮）\n主禮：我們若認自己的罪，上主是信實的，是公義的，必要赦免我們的罪，洗淨我們一切的不義。因此奉耶穌基督的名，你們的罪赦免了！\n會眾：奉耶穌基督的名，你的罪赦免了！\n全體：榮耀歸於上主。阿們。\n聖    道    禮\n（聆聽上主聖道）\n主禮：我們感謝上主賜下了生命的食糧。\n回應詩      【「你的話是我腳前的燈」《普天頌讚》637首】\n１．２│６－１２│３６５３│２－２３│５５３２│１－│１．２│６－│\n你　的  話　是　  我腳前的  燈，是 　 我路上的　光。  阿　　  們。\n頌  讀  經  課\n讀 經 經課一 使徒行傳4:32-35\n4:32 那許多信的人都是一心一意的，沒有一人說他的東西有一樣是自己的，都是大家公用。\n4:33 使徒大有能力，見證主耶穌復活；眾人也都蒙大恩。\n4:34 內中也沒有一個缺乏的，因為人人將田產房屋都賣了，把所賣的價銀拿來，放在使徒腳前，\n4:35 照各人所需用的，分給各人。\n啟 應 文： 詩篇133                                眾(坐）同應\n啟：看哪，弟兄和睦同居是何等地善，何等地美！\n應：這好比那貴重的油澆在亞倫的頭上，流到鬍鬚，又流到他的衣襟；\n合：又好比黑門的甘露降在錫安山；因為在那裡有耶和華所命定的福，就是永遠的生命。\n頌  榮   司會：我們要歸榮耀給上主。     ..................會眾（立）\n「但願榮耀，歸於父、子、聖靈，父、子、聖靈。\n起初這樣，現在這樣，以後也這樣，永無窮盡。阿們 阿們！」\n讀 經   經課二 約翰壹書1:1-2:2\n1:1 論到從起初原有的生命之道，就是我們所聽見、所看見、親眼看過、親手摸過的。\n1:2 這生命已經顯現出來，我們也看見過，現在又作見證，將原與父同在、且顯現與我們那永遠的生命、傳給你們。\n1:3 我們將所看見、所聽見的傳給你們，使你們與我們相交。我們乃是與父並他兒子耶穌基督相交的。\n1:4 我們將這些話寫給你們，使你們的喜樂充足。\n1:5 上帝就是光，在他毫無黑暗。這是我們從主所聽見、又報給你們的信息。\n1:6 我們若說是與上帝相交，卻仍在黑暗裡行，就是說謊話，不行真理了。\n1:7 我們若在光明中行，如同上帝在光明中，就彼此相交，他兒子耶穌的血也洗淨我們一切的罪。\n1:8 我們若說自己無罪，便是自欺，真理不在我們心裡了。\n1:9 我們若認自己的罪，上帝是信實的，是公義的，必要赦免我們的罪，洗淨我們一切的不義。\n1:10 我們若說自己沒有犯過罪，便是以上帝為說謊的，他的道也不在我們心裡了。\n2:1 我小子們哪，我將這些話寫給你們，是要叫你們不犯罪。若有人犯罪，在父那裡我們有一位中保，就是那義者耶穌基督。\n2:2 他為我們的罪作了挽回祭，不是單為我們的罪，也是為普天下人的罪。\n司會（啟）：這是上主的道。\n會眾（應）：感謝上主。\n福 音 書：約翰福音 20:19-31………………………………….主禮/會眾立\n*司會：會眾請起立！一同聆聽福音書的經課*\n主禮（啟）：主耶穌基督的福音是記載在約翰福音20：19～31\n會眾（應）：願榮耀歸於主基督\n20:19 那日（就是七日的第一日）晚上，門徒所在的地方，因怕猶太人，門都關了。耶穌來，站在當中，對他們說：願你們平安！\n20:20 說了這話，就把手和肋旁指給他們看。門徒看見主，就喜樂了。\n20:21 耶穌又對他們說：願你們平安！父怎樣差遣了我，我也照樣差遣你們。\n20:22 說了這話，就向他們吹一口氣，說：你們受聖靈！\n20:23 你們赦免誰的罪，誰的罪就赦免了；你們留下誰的罪，誰的罪就留下了。\n20:24 那十二個門徒中，有稱為低土馬的多馬；耶穌來的時候，他沒有和他們同在。\n20:25 那些門徒就對他說：我們已經看見主了。多馬卻說：我非看見他手上的釘痕，用指頭探入那釘痕，又用手探入他的肋旁，我總不信。\n20:26 過了八日，門徒又在屋裡，多馬也和他們同在，門都關了。耶穌來，站在當中說：願你們平安！\n20:27 就對多馬說：伸過你的指頭來，摸我的手；伸出你的手來，探入我的肋旁。不要疑惑，總要信。\n20:28 多馬說：我的主！我的上帝！\n20:29 耶穌對他說：你因看見了我才信；那沒有看見就信的有福了。\n20:30 耶穌在門徒面前另外行了許多神蹟，沒有記在這書上。\n20:31 但記這些事要叫你們信耶穌是基督，是上帝的兒子，並且叫你們信了他，就可以因他的名得生命。\n主禮（啟）：這是上主的福音。\n會眾（應）：願讚美歸與主基督。\n證    道\t光明的團契……………………………………………… 龐君華牧師\n回 應 詩   新普頌683「求賜智勇」……...………....…..…......…...領唱/眾立同頌\n信仰告白\t 使徒信經 （新普天頌讚封面）………………………………眾立同頌\n三一頌\t   普天之下萬國萬民，齊聲讚美父、子、聖靈。三位一體，\n同榮同尊，萬有之源，萬福之本。阿們。\n聖    餐    禮\n（獻上感恩的回應）\n請參閱聖餐禮文\n禱 告  \t\t\t\t\t\t\t\t\t\t\t            主 禮/會眾(坐)\n現在我邀請你們為上主的國以及我們所在的土地獻上我們的禱告\n會眾請靜默由主禮帶領會眾祈禱\n主禮結束禱告\n（＊＊週間請繼續參考本週代禱事項代禱＊＊）\n﹝詩歌回應﹞【「求聽我祈禱」《普天頌讚》634首】\n３３ ３ ３３│２────│４４ ４４４│３──３│\n求主 聽 我祈  禱，　 　   求主 聽我祈　禱；　求\n５．５５３│４──２│１－７２│１────│１－１－│\n主　側耳垂　聽，  並　賜　我平  安。　 　   阿　們。\n差    遣    禮\n報    告    …………………………………………………………司會／會眾(坐)\n差    遣\n﹝詩歌回應﹞ 主差遣我                                      會眾（立）唱\n１７６５ 　　 ５５∥１１．２２∥３－１ ３３│４２．１７│１─ ─ ─∥\n(主禮）主差遣我 (會眾) 主差  遣我  主差  遣  我 耶穌  求祢  差遣 我。\n我要出去      我要  出去  我要  出  去 奉主  聖名  今出 去。\n祝    福……………………………………………………………………龐君華牧師\n願主耶穌基督的恩惠，上主的慈愛，聖靈的團契，常與你們同在， 直到永遠。阿們！（林後13:13）\n【「三疊阿們」《新普天頌讚》第884首】\n殿樂\t退席╱熄燭                                        會（立）眾\n代  禱  關  懷\n請繼續為世界和平禱告\n◎印度每五年舉行一次的國會大選十六日揭開序幕，預料選後將會出現一個狀況不穩的聯合政府。7億多印度國民將有權投票，大選活動將持續一個月，並分5個階段。請為印度大選禱告，求主保守選舉過程的和平順利，也請主帶領印度人民選出合適的領導人。\n請為我們的社會禱告\n◎請繼續為台灣的失業率還有失業人口禱告，求主讓經濟早日復甦，讓失業人口都能找到合適的工作。\n◎請為台灣的經濟復甦、政治清明禱告，也為執政掌權者禱告，求主讓他們能有智慧、有能力領導國家，用主的道來治理國家。\n◎求主消弭我們社會中的族群對立及歧視。幫助寬容與理性的聲音能被聽見，使人和睦的行動有實際的效果。\n為教會及牧區的事工代禱\n◎為關懷之旅的預備及行程代禱，求主保守當天出入平安，並帶領我們將關懷帶到嘎色鬧部落。\n◎為牧區新的事工「城中人音樂沙龍─週五音樂會」的籌備與進行代禱。\n◎為「堂會學校」代禱，目前共分兩班，以實踐門徒關懷的「關懷實踐團契」以及慕道班為主，學員共計三十多人。\n◎為新的慕道課程「聖經這一本書」代禱，這是為已經受洗的初信者、或預備受洗者而預備個課程（目前有十位學員）。\n◎牧區基督教教育的事工：兒童主日學工作的人力，老師的身心靈健康，以及學員有效的學習。\n◎本（46）屆年議會的主題是「社關年」，求主教導我們如何關懷我們所在的土地。同時也為牧區會友及佈道委員會所規劃的外展工作代禱，如「城市關懷」活動中的城中人種籽教室（兒童工作）、城中人藝術工作坊童想音樂季（社區）等計畫。\n◎願各團契守約的精神能持續；並且期望牧區所有會友都能加入立約的群體（牧區內加入立約的團契有：衛青、衛蘭、衛家、衛智、姊妹會）。\n◎為學青團契的建立代禱，為他們能穩定參與團契生活並為這學期新約書信查經聚會代禱。\n◎為牧區辦公室工作的團隊守望禱告（牧師、師母、行政同工、幼稚園園長及教職員等）。\n◎為病痛中的會友或會友親屬守望禱告（參下表）\n姓       名\n目前狀況\n姓      名\n目前狀況\n陳  湜弟兄 （陳芝英姊妹之父）\n治療中\n胡王素藜姊妹\n血壓高\n宋李淑珍姊妹\n休養中\n蘇池秀珍姊妹\n休養中\n陳余玉對姊妹\n（陳馥蓮姊妹之母）\n休養中\n呂佳聲先生\n(呂若伶姊妹之父)\n鼻咽癌\n(休養中)\n高玉嬋姊妹\n腎臟病\n報　告　事　項\n歡迎第一次參加城中牧區崇拜的朋友。\n今天衛蘭團契的活動是「電影欣賞：刺激1995」，歡迎契友留步參加。\n牧區消息：\n衛智團契：本月份衛智團契將於本週二上午十點在副堂二樓舉行。活動為「群星會：歡唱我們的歌」。\n三、四月份執事會將合併召開，時間定於四月廿五日(六)上午十點，地點在副堂二樓，請執事和同工預留時間參加。\n財務委員會：奉獻收據上的金額有誤者，請洽趙華君姊妹。\n姊妹會：請繳交本年度會費六百元正給趙華君姊妹。\n崇拜與聖樂委員會：有興趣或感動想參與崇拜領唱服事的弟兄姊妹，請洽詩班指揮陳慧芳老師。\n社關委員會：五月二日(六)牧區將舉辦本年度的關懷之旅，本次參訪的對象是桃園縣復興鄉泰雅族嘎色鬧部落，詳情請參週報內頁海報，報名請洽林盈君姊妹。\n總會消息：\n青年事工委員會：2009年第五屆MYF青少年暑期營會將於七月七日至七月十一日於南投謝緯紀念營地舉行，歡迎國高中及大專學生參加。詳情及報名請洽林盈君姊妹。\n基督化家庭委員會：五月三十日(六)上午九點在陽明山福音園舉辦基督化家庭研習會，本項活動為免費，歡迎夫婦報名參加，細節請參佈告欄，報名請洽林盈君姊妹。\n本 月 壽 星\n4/20羅怡婷4/27李巧欣4/30呂成威\n活動消息\n時間\n聚會名稱\n負責人/講員或內容\n參與者\n地點\n4月19日(日)\n14:00pm\n學青小組\n提摩太前書\n契     友\n幼稚園教室\n4月19日(日)\n14:00pm\n衛蘭團契\n電影欣賞：刺激1995\n契     友\n副堂二樓\n4月21日(二)\n10:00am\n衛智團契\n群星會 歡唱我們的歌\n樂齡長者\n副堂二樓\n4月25日(六)\n14:30pm\n城中人種籽工作坊\n彩繪童心：藏在土裡的故事\n林志興老師、黃于庭老師\n國小學童\n幼稚園教室\n4月25日(六)\n17:00pm\n衛少團契\n團契活動\n契     友\n副堂二樓\n4月26日(日)\n12:30pm\n衛青團契\n讀書會：屬靈操練的禮讚─引導\n姚振銘弟兄\n契     友\n副堂三樓\n4月26日(日)\n12:30pm\n衛家團契\n讀書會：家庭是人生的冒險8\n契     友\n幼稚園教室\n4月26日(日)\n13:00pm\n城中牧區詩班\n聖樂欣賞：韋瓦第「四季」\n胡英宗弟兄\n開     放\n副堂二樓\n4月26日(日)\n14:00pm\n學青小組\n提摩太後書\n契     友\n地點待定\n4月26日(日)\n14:00pm\n衛蘭團契\n小組查經\n契     友\n副堂三樓\n\u0001\n撰文：胡英宗\n隆馬欽 Gavrül Lomakin (1812-1885)  我們讚美你Tebe Poem (Te Cantamus)\n歌詞(斯拉夫語)\nTebe poem我們讚美你Tebe blagoslovim 我們祝福你\nTebe blagodarim Gospodi 我們感謝你，親愛的救主\nI molim ti sya, Bozhe mash 我們向你祈禱，我們的神\n隆馬欽是俄羅斯的作曲家，本曲「我們讚美你」以緩慢、寧靜的和聲，唱出默想式的讚美，歌聲宏亮、熱誠，但不突兀，低沉而具磁性的男聲，直掏進會眾的內心深處，佇立在三位一體全能的神面前，敬虔地齊聲讚美，也展示出東方教會斯拉夫民族的崇拜特色。\n城中藝廊\n\u0001\n卡拉瓦喬\t1601-02年\n油彩、畫布107x146cm\n德國  波茨坦‧新宮藏\n由於多馬懷疑別的使徒轉述看見耶穌復活，在他們面前顯現，因此，耶穌真的在他及其他使徒面前現身，拉他的手摸觸自己的傷口，證明自己是真的復活了的救主。\n四個人表情豐富、動作誇張，耶穌右手拉著衣服，左手拉著多馬的手，導引著他伸出食指，插入右肋被長矛刺中的傷口裡，另兩位在多馬身後的門徒，也好奇地靠過來看個清楚。\n本構圖將四個人物緊湊在一起拉到前場，讓觀畫者有親臨現場感，也一起探究。\n角色選擇耶穌的氣宇軒昂、氣質不凡，有哲學家、神學家的味道。相較之下，另三位使徒則顯得粗俗不堪，多馬的衣服甚至殘破不堪，他們的頭髮蓬亂黝黑，滿臉皺紋，都是不修邊幅的鄉巴佬、農夫捆工的模樣，四個人物湊合一起，都區分出它的聖與俗。\n四個人物全拉到前景敘述，栩栩如生，光線從左邊照謝，與昏暗的背景形成強烈對比，讓主題更加生動。\n別的畫家畫多馬的懷疑都以遠景式手法，只在交代情節或故事。而卡拉瓦喬則能充分刻劃出多馬懷疑的眼光，用手指插進耶穌右肋的傷口裡，傷口畫的有血有肉，這一切都讓觀畫者如親臨現場，親自探索究竟。成了卡拉瓦喬最突出的巴洛克畫特色。\n復活主日\n2009.4.12\n各項聚會出席人數表\n早午堂聯合崇拜\n98人\n兒童主日學\n12人\n衛蘭團契\n6人\n學青小組\n8人\n復活期第三主日\n2009.4.26\n午堂服事人員表\n證道：\n龐君華牧師\n司會：\n余承祐先生\n司琴：\n李佳鴻先生\n司獻/招待：\n黃于庭女士\n復活主日\n2009.4.12\n奉獻明細表\n早堂崇拜\n10,660元\n0102\n4,000元\n0182\n3,000元\n0212\n6,000元\n0252\n8,000元\n0322\n1,000元\n0422\n3,000元\n0662\n5,000元\n0762\n3,000元\n0063\n1,300元\n仁愛捐\n452元\n特別捐\n特別捐\n受難日為嘎色鬧部落           3,300元\n0232（為關懷之旅）           1,000元\n0312（為嘎色鬧部落）         3,000元\n0075（為嘎色鬧部落）         1,000元\n感恩奉獻\n0003                         2,000元\n0312                         1,000元\n0772                          100元\n0015                         5,000元\n0075                         1,000元\n仁愛捐\n0642                         1,100元\n獻花\n0008                          500元\n0762                          500元\n獻刊\n0512                          300元\n0522                          300元\n其他\n謝幸美                       2,000元\n合計\n67,512元\n衛理公會城中牧區的呼召\n就是在基督的愛中回應上主的福音，我們透過崇拜、\n學習與關顧、服務、傳揚福音來活出基督門徒的身分。\n城中牧區（2009年4月19日–2009年4月26日）聚會時間與內容\n時間\n聚會名稱\n聚會內容\n講員\n地點\n日\n10:00~11:00\n早堂崇拜\n復活期第二主日\n龐君華牧師\n會　　堂\n10:00~11:00\n兒童主日學\n兒童主日學\n蔡孟庭姊妹\n黃于庭姊妹\n袁淑靜姊妹\n副堂二樓\n12:30~14:00\n午堂崇拜\n復活期第二主日\n龐君華牧師\n會    堂\n14:00~16:00\n學青小組\n查經會：提摩太前書\n陳晶晶姊妹\n副堂三樓\n14:00~16:00\n衛蘭團契\n電影欣賞：刺激1995\n契      友\n副堂二樓\n二\n10:00~12:00\n衛智團契\n群星會：歡唱我們的歌\n樂齡長者\n副堂二樓\n四\n19:30~21:00\n堂會學校\n關懷實踐團契\n慕道班\n信徒生活：登山寶訓4\n龐君華牧師\n副堂二樓\n六\n14:30~16:30\n城中人種籽工作坊\n彩繪童心\n藏在土裡的故事\n林志興老師\n黃于庭老師\n幼稚園教室\n17:00~19:00\n衛少團契\n團契活動\n契      友\n副堂二樓\n日\n09:00~09:45\n獻詩練習\n奇異的恩典\n王守誠老師\n張桂華老師\n會    堂\n09:45~10:00\n會前領唱\n新普天頌讚：49、52、717\n胡瑠美姊妹\n會    堂\n10:00~11:00\n早堂崇拜\n復活期第三主日\n劉瑞河弟兄\n會　　堂\n10:00~11:00\n兒童主日學\n兒童主日學\n丁安萍姊妹\n陳宬霖姊妹\n楊肇悅姊妹\n副堂二樓\n12:30~14:00\n午堂崇拜\n復活期第三主日\n龐君華牧師\n會　　堂\n12:30~14:30\n衛青團契\n屬靈操練的禮讚─引導\n姚振銘弟兄\n副堂三樓\n12:30~14:30\n衛家團契\n讀書會\n契      友\n幼稚園教室\n13:00~14:30\n城中牧區詩班\n聖樂欣賞\n胡英宗弟兄\n副堂二樓\n14:00~16:00\n學青小組\n查經會：提摩太後書\n契      友\n戶    外\n14:00~16:00\n衛蘭團契\n小組查經\n契      友\n副堂二樓\n復活期第三主日\n使徒行傳 3:12-19             詩篇4\n約翰壹書 3:1-7               約翰福音24:36b-48", "nchars": 8111, "source_file": "周報/2009/四月份/09-04-19wf主日崇拜程序1e.doc", "ext": ".doc"}