{"date": "2019-05-05", "service": "主日崇拜", "season": "復活期第三主日", "date_text": "主後二○一九（民108）年五月五日", "color": "白", "preacher": "龐君華牧師", "presider": "蕢建華會督", "sermon_title": "你來跟從我吧！", "roles": {"主禮": "蕢建華會督", "證道": "龐君華牧師", "司會": "周慶同弟兄", "讀經": "翁嘉慶弟兄", "司琴": "林敬弟兄", "獻花": "翁其振弟兄", "領唱": "林盈君姊妹", "獻刊": "顧孟真姊妹", "招待": "楊秀惠姊妹", "兒童主日學": "楊肇悅姊妹\n唐乃華姊妹", "司獻": "李意慧姊妹\n楊秀惠姊妹"}, "scriptures": ["路加福音24:34", "使徒行傳 9:1-20", "啟示錄5:11-14", "約翰福音21:1-19", "約翰福音 21:1-19"], "hymns": [{"book": "新普頌", "no": "458", "title": "赴主宴席"}, {"book": "世紀頌讚", "no": "339", "title": "向高處行"}, {"book": "新普頌", "no": "288", "title": "復活基督"}, {"book": "新普天頌讚", "no": "884", "title": "）………..……...….…………眾立"}], "full_text": "復活期第三主日\n主後二○一九（民108）年五月五日上午十時正\n白色象徵純潔、喜樂和真理的光輝，用於與主基督直接有關的節期，如聖誕期、復活期、顯現日、\n升天日、聖三一主日、基督登山變容主日。\n***崇拜進行時，請暫時關閉您身上的行動電話及呼叫器***\n入殿禮\n詩歌領唱 ………………………………………….……….……. 林盈君姊妹\n默想音樂 ………………………………………….……….……. 姚振銘弟兄\nByrd：ChristusresurgensI2:52\nChristusresurgens ex mortuis jam non moritur:morsilli ultra non dominabitur.Quod enimvivit, vivitDeo. Alleluia.\n基督既從死人中復活，就不再死，死也不再作他的主了，他活，是對上帝活著。阿利路亞！(羅6:9&10b)\n序    樂 ……………….…………………………………………………司琴\n安 靜 頌 …【「主在聖殿中」《新普天頌讚》784首】………眾(坐)肅靜\n主在聖殿中，主在聖殿中，普天下的人，\n在主面前，都應當肅靜，肅靜，肅靜，應當肅靜。阿們。\n宣    召 ………………………………………………..…………………司會\n主果然復活（路加福音24:34a）\n頌    讚 新普頌458首「赴主宴席」………………….… 領唱╱眾立同頌\n(第1、2節→間奏→第3節)\n始 禮 文\n啟：與我們的主同行，使我們得見來自上天的榮光！\n應：領我向高處前進，儘管那光芒使人目盲。\n啟：與我們的主同行，使我們得聽來自天上的聲音！\n應：領我向高處前進，儘管那聲波是我耳所不能承受。\n啟：與我們的主同行，使我們學到生命的功課。\n應：領我向高處前進，儘管這功課帶著考驗。\n啟：我們要與主同行到錫安，那座落在佳美之處的山城。\n合：我們要與主前進到天上的錫安，那是天上榮耀的聖城。\n祈    禱 ………………………\t……………………………………司會/眾立\n主 禱 文 …【「主禱文」《普天頌讚》649首】……………………司會/眾立\n我們在天上的父，願人都尊父的名為聖。\n願父的國降臨。願父的旨意，行在地上，如同行在天上。\n我們日用的飲食，求父今日賜給我們。\n又求饒恕我們的罪，如同我們饒恕得罪我們的人。\n不叫我們遇見試探，拯救我們脫離兇惡。\n因為國度，權柄，榮耀全是父的直到永遠。阿們。\n詩    歌 世紀頌讚339首「向高處行」(請參週報第6頁)….…….…司會/眾坐\n(第1、4節齊唱→第2節女聲→第3節男聲)\n聖道禮\n祈光禱文 ………………………..…………………………………………全體\n司會：我們一同求主賜下亮光！\n會眾：復活的主耶穌，祢讓門徒充滿了勇氣與希望：請也讓我們剛強壯膽去見證祢復活的生命，此刻請藉著祢的聖言對我們說話。奉主耶穌基督的名。阿們。\n讀    經 ………………………………………….…………..……翁嘉慶弟兄\n經 課 一 使徒行傳 9:1-20  (新約192頁)\n啟 應 文 詩篇30:1-12  …………………………….…………..…… 眾坐同應\n啟：耶和華啊，我要尊崇你，因為你救了我，不讓仇敵向我誇耀。\n應：耶和華－我的上帝啊，我呼求你，你醫治了我。\n啟：耶和華啊，你救我的性命脫離陰間，使我存活，不至於下入地府。\n應：耶和華的聖民哪，你們要歌頌他，要頌揚他神聖的名字。\n啟：因為，他的怒氣不過是轉眼之間，他的恩典乃是一生之久；一宿\n雖然有哭泣，早晨便必歡呼。\n應：至於我，我凡事順利，就說：「我永不動搖。」\n啟：耶和華啊，你曾施恩，使我穩固如山；你轉臉不顧，我就驚惶。\n應：耶和華啊，我曾求告你；我向耶和華懇求：\n啟：「 我被害流血，下到地府，有何益處呢？塵土豈能稱謝你、傳揚\n你的信實嗎？\n應：耶和華啊，求你應允我，憐憫我！耶和華啊，求你幫助我！」\n啟：你將我的哀哭變為跳舞，脫去我的麻衣，為我披上喜樂，\n合：使我的靈歌頌你，不致緘默。耶和華－我的上帝啊，我要稱謝你，直到永遠！\n榮 耀 頌 …………………………………………….………….…………眾立\n「但願榮耀，歸於父、子、聖靈，父、子、聖靈。\n起初這樣，現在這樣，以後也這樣，永無窮盡。阿們阿們！」\n經 課 二 啟示錄5:11-14       (新約404頁)\n啟：這是上主的道\n應：感謝上主\n獻    詩 … 你的罪雖像朱紅 ………………….…………..…城中男聲詩班\n你的罪雖像朱紅，主必使它白如雪。x2 主有偉大的憐憫，與奇妙的愛，請聽主慈愛呼聲，x2 快回轉歸向真神，x2\n你的罪祂肯赦免，從今後永不紀念。x2 主你的神已曉諭當仰望救主。你的罪祂肯赦免x2 從今後永不紀念x2\n福音前禱 【「你的話是我腳前的燈」《新普天頌讚》832首】…司會/眾立\n「你的話是我腳前的燈，是我路上的光。阿們。」\n司會（啟）：主耶穌基督的福音是記載在約翰福音21:1-19\n會眾（應）：願榮耀歸於主基督。\n福 音 書 …\t約翰福音 21:1-19  (新約176頁) ……….…………司會/會眾立\n司會（啟）：這是上主的福音。\n會眾（應）：願讚美歸與主基督。\n證    道 .……….….….你來跟從我吧！ …………….…….… 龐君華牧師\n回 應 詩 ...新普頌288首「復活基督」.………..…..…….……司會/會眾立\n(第1-2節→間奏→第3-4節)\n信仰告白 …使徒信經（參新普頌封面裏頁）…….…..….……… 眾立同頌\n聖 餐 禮 …………………………………………………………. 蕢建華會督\n奉    獻 (第一次所收奉獻為教會聖工，第二次所收奉獻用作慈善用途的仁愛捐) … 眾樂意\n司會：我們既然成為罪蒙赦免，與上帝和好的子民，讓我們把自己和禮物獻給上主。\n會眾：（奉獻後頌唱：「向主獻呈」）凡我向主所呈，都是主賜的恩，凡我所有，都屬於主，是主託付僕人。\n報    告 ……………………………………..…………...……..…………司會\n牧    禱 …………………………………………………..….……龐君華牧師\n差遣禮\n三 一 頌 ………………………………………..………..…….………… 眾立\n普天之下萬國萬民，齊聲讚美父、子、聖靈。\n三位一體，同榮同尊，萬有之源，萬福之本。阿們。\n祝    福 …………………………...……..……….….…..……… 蕢建華會督\n賞賜平安的上帝，已經使我們的主耶穌，就是那群羊的大牧人，從死裡復活；也使你們在各樣善工上，完全遵行他的旨意。又願全能的上帝，聖父、聖子、聖靈，賜福給你們，直到永遠，阿們。\n阿 們 頌 …………（新普天頌讚884首）………..……...….…………眾立\n退 殿 曲 …天庭歌頌上主（泰澤詩選）……….…………………眾立同頌\n天庭歌頌上主，大地讚美上主，基督耶穌祂已真復活…\n週五認識基督信仰課程《衛斯理教你如何蒙恩》\n剛完成C.S. Lewis的名著《返璞歸真》（原書名為如此基督教），他的最後結論討論基督信仰的重點，在經歷成為「新人」。然而如何持續「新人」的生活，正是我們會祖衛斯理約翰綜合基督信仰所提出的方向。所以我們將以這本作為我們新一階段的討論。\n作者：Steve Harper譯者：方蔚芸\n內容簡介：有人以為循道衛理宗只注重「循規蹈矩」，現行矩步方方正正，其實不然。會祖約翰衛斯理強調「基督徒的完全」，但這「完全」原來是通向喜樂與得勝之門，是上帝賜恩福的通路。本書深入淺出地介紹蒙恩生活的祕訣，讀後令你茅塞頓開。\n城中姊妹會消息\n五月份姊妹會活動\n陽明山竹子湖賞繡球花\n日期：２０１９年５月１８日\n時間：０９：００劍潭捷運站１號出口\n１５：００回到劍潭捷運站\n請向姊妹會李幸真姊妹報名，或洽辦公室\n聯絡人：李幸真０９３５１７６１４４\n備註：當日遇雨則調整行程，請洽聯絡人\n城中姊妹會敬邀\n報告事項\n歡迎今天第一次參與我們崇拜的朋友，我們期待有機會多認識您們，也邀請您會後與我們一起享用午餐愛筵。\n今天下午牧師與詩班將前往伊甸興隆養護中心（原一壽）主持聖餐禮拜，有意前往服事的會友，請於13:50在教會門口集合。\n姊妹會：5月18日將到陽明山竹子湖賞繡球花，欲參加的弟兄姊妹請向李幸真或陳香杏姊妹報名，詳情請參第7頁。\n總會消息：五月廿五日(六)上午9點正在台北衛理堂舉行第56屆第二次年議會閉幕禮拜暨會督就職及牧職按立禮，歡迎弟兄姊妹參加。\n每週五（5/3）晚的基督信仰班，已開始新的閱讀及討論，《衛斯理教你如何蒙恩》，詳情請參第7頁，歡迎參加。\n為我們所在的土地與社會及世界守望\n為我們所居住的土地\n為我們所在社會真正和諧祈禱，無論族群、省籍、世代、職業間彼此包容接納。也為公義制度建立，包括司法、金融、經濟、土地等的公平正義代禱。\n為在社會中從事各樣服務、教育、公益、文化的非牟利或非政府組織的工作人士代禱，請主加添他們的力量與毅力。\n為社會中家中有家人長期患病，需要照顧家庭，為獨居的長者的照料祈禱。\n為社會中的勞工朋友代禱，願有一個安全、尊嚴及合理報酬的工作環境。。\n為我們的年議會與牧區\n請為本堂58週年堂慶後，繼續堂慶的目標「成為真實的門徒群體」，朝向總會的目標「徹底的門徒」的概念，其推廣與落實代禱。\n請為會友們身心靈的健康代禱。並為牧區各小組及團契禱告，希望更多會友參與團契生活，一同學習「成為真實的門徒」。\n為會友們的身心靈健壯代禱，為在病痛中及手術後恢復中以及復健中的會友們祈禱，也為正承受各樣生活壓力的會友祈禱。\n請為本屆年議會後本會的發展，年議會新團隊的預備，及本堂牧者、牧養事工的銜接代禱。\n為普世教會\n為普世教會的合一，在世上作美好的見證。\n為兩岸的和諧、世界的和平代禱，為國與國之間能在經濟、環保及糧食問題的合作共同面對世上的種種問題祈禱。\n為斯里蘭卡阿努拉德普勒區（Anuradhapura District）及中國大陸正受到逼迫的教會祈禱。\n為每個家庭，以及兒童都能得到適當的照顧與正確的價值觀教育祈禱。\n為各地因戰禍以及因氣候變遷所造成流落的難民祈禱。\n為還不認識耶穌的人、對信仰或教會感到失望、懷疑的人、因為恐懼而失去力量的人、需要信心、愛心與勇氣的人祈禱。\n丙年(第23週)每日經課\n復   活   期  第  二  主   日\n20190428\n各項聚會出席人數表\n復活期第四主日\n20190512\n早堂服事人員表\n復活期第二主日\n20190428\n奉獻明細表\n衛理公會城中牧區的呼召\n就是在基督的愛中回應上主的福音，我們透過崇拜、\n學習與關顧、服務、傳揚福音來活出基督門徒的身分。\n內尋靈性深度 外展生活服務\n城中牧區（2019年5月5日–2019年5月12日）聚會時間與內容\n復活期第四主日", "nchars": 4289, "source_file": "周報/2019/19-05-05主日崇拜程序5e.docx", "ext": ".docx"}