{"date": "2006-04-09", "service": "午堂", "season": "棕樹主日", "date_text": "主後二○○六年四月九日", "color": "紫", "preacher": "龐君華牧師", "presider": "龐君華牧師", "sermon_title": "落在地裡的麥子", "roles": {"主禮": "龐君華牧師", "證道": "龐君華牧師", "司會": "羅怡婷女士", "司琴": "劉芳良女士", "講員": "龐君華牧師", "讀經": "劉博樺弟兄", "兒童主日學": "楊肇悅姊妹", "司獻": "焦瑬弟兄", "獻花": "黃運湘弟兄", "獻刊": "胡瑠美姊妹"}, "scriptures": ["馬可福音11:1~11", "腓立比書2:5～11", "馬可福音15:1～39", "耶利米書31:31~34", "希伯來書5:5~10", "約翰福音12:20~33", "哥林多前書15:1～11", "約翰福音20:1～18"], "scripture_ref": "經課一：馬可福音11:1~11；經課二：腓立比書2:5～11；福音書：馬可福音15:1～39", "scripture_labeled": true, "hymns": [], "full_text": "中華基督教衛理公會城中牧區午堂崇拜\n棕樹主日\n主後二○○六年四月九日\n（紫）\n主禮/證道：龐君華牧師\n司會：羅怡婷女士\n司獻/招待/：李佳鴻先生\n司琴：劉芳良女士\n紫色象徵懺悔、警醒與禁戒，用於懺悔與等候的節期，如將臨期、大齋期等\n***崇拜進行時，請暫時關閉您身上的行動電話及呼叫器***\n預    備    禮\n（朝見上主的準備）\n序   樂      請會眾靜默，預備心進入崇拜                           （點燃燭光）\n宣    召\t你們當克苦己心，在主前深切省察！仰望上主的恩典…................ 司   會\n頌    讚\t聯86「至聖之首受重創」  \t………..…….....................司會╱眾立同頌\n始 禮 文\n啟：主是生命的主，祂所賜的生命連死亡也不能拘禁，\n應：主啊！願你的靈來，使我們了靈性復甦。\n啟：在絕望的枯骨中，上主使其長盼望的筋與肉。\n應：主啊！願你的靈來，使我們了滿有盼望。\n啟：我們因罪而死的身體，也要因主的靈，在義中活過來。\n應：主啊！願你的靈來，燃起我們復活的嚮往。\n合：主啊！願你的光明消除死亡的恐懼與失望的陰霾。阿們\n懺      悔      禮\n心中潔淨文\t\t……………………………………………………………………（司   會）\n全能的上主，所有人的心，在主面前都無不顯明。\n心裡所羨慕的主都知道，心裡所隱藏的，也瞞不過主。\n求主用聖靈感化，潔淨我們內心的意念，使我們盡心愛主，\n恭敬歸榮耀與主的聖名。這都是靠著我們的主耶穌基督。阿們。\n召   喚\t「弟兄姊妹！請我們安靜自己的心，誠實省察自己對上主\n對人是否盡了當盡的本分！」\n靜   默\n﹝詩歌回應﹞求主憐憫詞                                              會眾坐唱\n６１３３│３２ １２３－│３５ ５ ６５６│\n求主憐憫 我　　　 們；　求基 督 憐  憫\n２１２－│６１３２│７　５６－│\n我　們； 求主憐憫  我    們。\n認罪文\t\t………………………………………………………………（會   眾）\n啟：我說我要向上主承認我的過犯；\n應：「最慈悲的上主，\n我們承認在思想、言語、行為上，常常得罪了祢；\n應做的不做，不應該做的反去做。\n我們沒有盡心愛祢；也沒有愛人如己。\n現在我們痛心懊悔，懇求祢施憐憫，\n為了聖子耶穌基督，\n饒恕我們的已往，\n扶助我們的現在，\n引導我們的將來；\n好叫我們樂意遵行祢的旨意，\n蒙祢的悅納，而歸榮耀給祢的聖名。阿們。」\n安慰文\t\t………………………………………………………………….…（主   禮）\n主禮：請聽這好消息：當我們還是罪人時,基督已為我們死；上主的愛在此就向我們顯明了。奉耶穌基督的名，你們的罪赦免了！\n會眾：奉耶穌基督的名，你的罪赦免了！\n全體：榮耀歸於上主。阿們。\n聖    道    禮\n（聆聽上主聖道）\n祝文\n主禮：願主與你同在。\n會眾：願主也與你同在。\n主禮：我們感謝上主賜下了生命食糧。\n回應詩      【「你的話是我腳前的燈」《普天頌讚》637首】\n１．２│６－１２│３６５３│２－２３│５５３２│１－│１．２│６－│\n你　的 話　是　  我腳前的 燈，是 　 我路上的　光。 阿　　們。\n頌  讀  經  課\n讀 經  經課一馬可福音11：1~11………………………………………司會\n11:1 耶穌和門徒將近耶路撒冷，到了伯法其和伯大尼，在橄欖山那裏；耶穌就打發兩個門徒，\n11:2 對他們說：你們往對面村子裏去，一進去的時候，必看見一匹驢駒拴在那裏，是從來沒有人騎過的，可以解開，牽來。\n11:3 若有人對你們說：為甚麼作這事？你們就說：主要用牠。那人必立時讓你們牽來。\n11:4 他們去了，便看見一匹驢駒拴在門外街道上，就把他解開。\n11:5 在那裏站著的人，有幾個說：你們解驢駒作甚麼？\n11:6 門徒照著耶穌所說的回答，那些人就任憑他們牽去了。\n11:7 他們把驢駒牽到耶穌那裏，把自己的衣服搭在上面，耶穌就騎上。\n11:8 有許多人把衣服鋪在路上，也有人把田間的樹枝砍下來，鋪在路上。\n11:9 前行後隨的人都喊著說：和散那（和散那：原有求救的意思，在此乃是稱頌的話）！奉主名來的是應當稱頌的！\n11:10 那將要來的我祖大衛之國是應當稱頌的！高高在上和散那！\n11:11 耶穌進了耶路撒冷，入了聖殿，周圍看了各樣物件。天色已晚，就和十二個門徒出城，往伯大尼去了。\n啟 應 文\t詩篇118：1～2、19～29\t............................................................眾坐同應\n啟：你們要稱謝耶和華，因他本為善；他的慈愛永遠長存！\n應：願以色列說：他的慈愛永遠長存！\n啟：給我敞開義門；我要進去稱謝耶和華！\n應：這是耶和華的門；義人要進去！\n啟：我要稱謝你，因為你已經應允我，又成了我的拯救！\n應：匠人所棄的石頭已成了房角的頭塊石頭。\n啟：這是耶和華所做的，在我們眼中看為希奇。\n應：這是耶和華所定的日子，我們在其中要高興歡喜！\n啟：耶和華啊，求你拯救！耶和華啊，求你使我們亨通！\n應：奉耶和華名來的是應當稱頌的！我們從耶和華的殿中為你們祝福！\n啟：耶和華是上主；他光照了我們。理當用繩索把祭牲拴住，牽到壇角那裏。\n應：你是我的上主，我要稱謝你！你是我的上主，我要尊崇你！\n合：你們要稱謝耶和華，因他本為善；他的慈愛永遠長存！\n頌   榮  司會：我們要歸榮耀給上主。\t　　...................會眾（立）\n「但願榮耀，歸於父、子、聖靈，父、子、聖靈。\n起初這樣，現在這樣，以後也這樣，永無窮盡。阿們 阿們！」\n讀 經    經課二　腓立比書2：5～11……………………………………司會\n2:5 你們當以基督耶穌的心為心：\n2:6 他本有上主的形像，不以自己與上主同等為強奪的；\n2:7 反倒虛己，取了奴僕的形像，成為人的樣式；\n2:8 既有人的樣子，就自己卑微，存心順服，以至於死，且死在十字架上。\n2:9 所以，上主將他升為至高，又賜給他那超乎萬名之上的名，\n2:10 叫一切在天上的、地上的，和地底下的，因耶穌的名無不屈膝，\n2:11 無不口稱耶穌基督為主，使榮耀歸與父上主。\n司會（啟）：這是上主的道。\n會眾（應）：感謝上主。\n福音書：馬可福音15：1～39……………………………………………主禮\n15:1 一到早晨，祭司長和長老、文士、全公會的人大家商議，就把耶穌捆綁，解去交給彼拉多。\n15:2 彼拉多問他說：你是猶太人的王嗎？耶穌回答說：你說的是。\n15:3 祭司長告他許多的事。\n15:4 彼拉多又問他說：你看，他們告你這麼多的事，你甚麼都不回答麼？\n15:5 耶穌仍不回答，以致彼拉多覺得希奇。\n15:6 每逢這節期，巡撫照眾人所求的，釋放一個囚犯給他們。\n15:7 有一個人名叫巴拉巴，和作亂的人一同捆綁。他們作亂的時候，曾殺過人。\n15:8 眾人上去求巡撫，照常例給他們辦。\n15:9 彼拉多說：你們要我釋放猶太人的王給你們嗎？\n15:10 他原曉得，祭司長是因為嫉妒才把耶穌解了來。\n15:11 只是祭司長挑唆眾人，寧可釋放巴拉巴給他們。\n15:12 彼拉多又說：那麼樣，你們所稱為猶太人的王，我怎麼辦他呢？\n15:13 他們又喊著說：把他釘十字架！\n15:14 彼拉多說：為甚麼呢？他作了甚麼惡事呢？他們便極力的喊著說：把他釘十字架！\n15:15 彼拉多要叫眾人喜悅，就釋放巴拉巴給他們，將耶穌鞭打了，交給人釘十字架。\n15:16 兵丁把耶穌帶進衙門院裏，叫齊了全營的兵.。\n15:17 他們給他穿上紫袍，又用荊棘編作冠冕給他戴上，\n15:18 就慶賀他說：恭喜，猶太人的王啊！\n15:19 又拿一根葦子打他的頭，吐唾沫在他臉上，屈膝拜他。\n15:20 戲弄完了，就給他脫了紫袍，仍穿上他自己的衣服，帶他出去，要釘十字架。\n15:21 有一個古利奈人西門，就是亞力山大和魯孚的父親，從鄉下來，經過那地方，他們就勉強他同去，好背著耶穌的十字架。\n15:22 他們帶耶穌到了各各他地方（各各他繙出來就是髑髏地），\n15:23 拿沒藥調和的酒給耶穌，他卻不受。\n15:24 於是將他釘在十字架上，拈鬮分他的衣服，看是誰得甚麼。\n15:25 釘他在十字架上是巳初的時候。\n15:26 在上面有他的罪狀，寫的是：猶太人.的王。\n15:27 他們又把兩個強盜和他同釘十字架，一個在右邊，一個在左邊。（有古卷在此有：\n15:28 這就應了經上的話說：他被列在罪犯之中。）\n15:29 從那裏經過的人辱罵他，搖著頭說：咳！你這拆毀聖殿、三日又建造起來的，\n15:30 可以救自己，從十字架上下來吧！\n15:31 祭司長和文士也是這樣戲弄他，彼此說：他救了別人，不能救自己。\n15:32 以色列的王基督，現在可以從十字架上下來，叫我們看見，就信了。那和他同釘的人也是譏誚他。\n15:33 從午正到申初，遍地都黑暗了。\n15:34 申初的時候，耶穌大聲喊著說：以羅伊！以羅伊！拉馬撒巴各大尼？繙出來就是：我的上主！我的上主！為甚麼離棄我？\n15:35 旁邊站著的人，有的聽見就說：看哪，他叫以利亞呢！\n15:36 有一個人跑去，把海絨蘸滿了醋，綁在葦子上，送給他喝，說：且等著，看以利亞來不來把他取下。\n15:37 耶穌大聲喊叫，氣就斷了。\n15:38 殿裏的幔子從上到下裂為兩半。\n15:39 對面站著的百夫長看見耶穌這樣喊叫（有古卷沒有喊叫二字）斷氣，就說：這人真是上主的兒子！\n主禮（啟）：這是上主的福音。\n會眾（應）：願讚美歸與主基督。\n證    道\t   受苦的基督……………………...……….…….……………龐君華牧師\n回 應 詩\t聯82「寶架清影」\t……………….….......…..…...……..… 眾立同頌\n信仰告白\t使徒信經\n主禮： 讓我們承認我們的信仰\n全體：「我信上帝，全能的父，創造天地的主。\n我信我主耶穌基督，上帝的獨生子，因聖靈感孕，由童貞女馬利亞所生，\n在本丟比拉多手下受難，被釘於十字架，受死、埋葬、降在陰間，\n第三天從死人中復活、升天，坐在全能父上帝的右邊，\n將來必從那裡降臨，審判活人死人。\n我信聖靈，我信聖而公之教會，我信聖徒相通，我信罪得赦免，\n我信身體復活，我信永生。」\n三一頌\t普天之下萬國萬民，齊聲讚美父、子、聖靈。三位一體，\n同榮同尊，萬有之源，萬福之本。阿們。 【「三一頌」《普天頌讚》封底內頁】\n聖    餐    禮\n（在恩典中的回應）\n請參閱聖餐禮文\n差    遣    禮\n祝   福\t\t                                                   （主   禮）\n基督賜恩給你們在聖潔的生活上長進，能捨棄自己，背起自己的十字架追隨基督，又願願我主耶穌基督的恩惠，天父上主的慈愛，聖靈保惠師的團契與引導，常與你們眾人同在，從今時直到永永遠遠。阿們。\n阿們頌【「三疊阿們」《聯合詩選》第247首】\n差   遣\n主禮：上主的兒女，你們為何在此？\n會眾：我們受差遣一起面對真實的世界\n主禮：基督已經勝過了世界。\n會眾：我們一起經歷基督的勝利，\n合：阿們！！\n禮成/默禱/殿樂\t                                        （熄滅燭光）\n**禮成後請仍保持默檮，待殿樂結束後才開始活動**\n報　告　事　項\n歡迎第一次參加城中牧區崇拜的朋友。\n下週主日為復活主日，早午堂合併崇拜，歡迎弟兄姐妹參加早上十點崇拜。\n會友陳振興、陳芝英伉儷於四月五日下午增添新成員陳奕新小弟弟，分娩過程順利，母子均安。\n本週主日（棕樹主日）開始的受難週，牧區於週間舉辦各個不同的特別崇拜：聖週四（4/13）晚上七時半為逾越節晚餐崇拜；受難日（4/14）晚上七時半為受難日晚崇拜—「被遺忘的苦難」，邀請台北聖樂團獻詩─古諾的「G大調莊嚴彌撒」。請會友利用辦公室製作的邀請卡，邀請朋友參加。\n（欲參加逾越節晚餐崇拜的會友，須報名並繳交餐費新台幣一百元，請於今日崇拜結束後與辦公室洽。）\n因為受難日崇拜的緣故，本週四晚的堂會學校暫停一次。\n牧區MYF衛青團契將於四月十五日(六)下午兩點，邀請天力亞太台灣分公司顧問魏懋文姊妹來分享：「性格v.s職場人際互動」，歡迎有興趣或在職場遇到人際問題的在職青年們來參加。\n下週主日為復活節，牧區照往例於上午七時至八時舉行朝陽崇拜，並且供應早餐，請參加的會友預先登記，方便預備用餐人數。十時正為早午堂聯合崇拜，會中將有城中詩班、城中幼稚園獻詩及安德石弟兄、張桂華姊妹的獻奏等，以紀念主耶穌的復活。\n堂會學校將開新的課程，「信仰分享課程」與「讀書會的帶領」，這兩項課程為提供會友參與牧區外展事工的基本訓練之一；下個月開始的「關懷佈道課程」為預備材料，請會友事先向辦公室報名，。\n請會友留意教育委員會的「讀經推廣活動」，並歡迎提供每日讀經心得。\n姊妹會將於四月十五日中午十二時在陽明山福音園聚會，請有意參與者向趙華君姊妹報名。\n請各團契單位若有消息或活動欲刊登於週報，請在星期四中午前，以書面傳真2392-2980或來電2393-0705或電子郵件cmpc@fhl.net通知辦公室同工，以便及時登上周報。\n牧區MYF青少年團契工作，除了青少年主日外，亦於每週六下午二時正亦開始團契聚會時間，聚會節目如下：\n時間\n主題\n輪值輔導\n備註\n4/15\n作文班/拜訪神秘家庭\n黃于庭姊妹\n張心怡姊妹\n4/22\n電影欣賞\n黃于庭姊妹\n4/29\n專題分享\n張心怡姊妹\n代  禱  關  懷\n1、請繼續為世界和平禱告\n◎伊朗近來頻頻舉行軍事演習、展示軍力，並不願接受國際社會對其核武問題的監督，中東情勢為之緊張。請為世界和平禱告，求上帝賜下平安，平息世上的爭端，使世人免於戰禍，使我們真正享有長久的和平。\n◎請為饑荒地區的人民禱告，願上主眷顧，使受苦者得安慰、使饑餓者得飽足，也願上主賜憐憫心給富裕國家的政府與人民，使富國願意向窮國伸出援手，助窮國人民度過難關。\n2、請為我們的社會禱告\n◎請為我們的公部門禱告，近來許多瀆職或官員私德問題相繼浮現，政府的公信力頗受質疑，請為官員的心懷意念禱告，求上帝賜他們公義的心，使公僕們真正潔身自愛、廉能任事，使我們社會能夠找回對公部門的信任。\n◎請為新移民及外籍勞工禱告，願上帝格外恩待他們，使他們在台灣這塊土地上得到真正平等的對待，並求主賜智慧給移民及勞工主管當局，使我們的政府找出扶助及保障新移民及外籍勞工的合宜措施。\n3、請為牧區及衛理公會代禱：\n◎為大齋期的各項禮拜及靈修活動的籌備工作代禱。\n◎目前教堂兩側都有建築工程，希望這些工程對堂會的建築、各項事工、幼稚園的教育等的影響能減到最低。\n◎為信徒教育的事工：堂會學校（主日學）、紅本門徒、慕道班等課程等代禱。\n◎外展工作「城市關懷」活動的籌備，目前活動有少年創意作文班、社區親子講座、城中人生活沙龍、城中人藝術工作坊等計畫。\n◎為牧區各委員會的會議與同工的召集禱告，希望更多會友投入事奉。為牧區推動禱告月會、每日讀經的等事工代禱。\n◎為會友們渴慕主道，建立家庭及個人的見證生活代禱。為牧區各階段的修繕計畫代禱。\n4、請會友彼此代禱：\n◎為病痛中的會友或會友親屬守望禱告（參下表）\n姓       名\n目前狀況\n姓      名\n目前狀況\n陳  湜弟兄 （陳芝英姊妹之父）\n復建中\n胡王素藜姊妹\n血壓\n宋李淑珍姊妹\n膝蓋關節手術 休養中\n蘇池秀珍姊妹\n住院治療中\n吳美麗姊妹\n(黃玲媛姊妹之母)\n療養中\n鄭段宛琪姊妹\n復建中\n胡英宗弟兄\n休養中\n陳余玉對姊妹 （陳馥蓮姊妹之母）\n手術後休養中\n黃慈錄弟兄\n(黃冬玫姊妹之父)\n脊椎側彎壓迫神經\n焦  璽弟兄\n(焦瑬弟兄之兄)\n多發性腦血栓\n冠狀心臟病\n徐瑋良弟兄\n右手右腳骨折 休養中\n陳美月姊妹\n(黃冬玫姊妹之母)\n輕微中風\n治療中\n本 月 壽 星\n4/2鍾歆宜 4/20羅怡婷 4/23姚慶邦 4/30呂成威\n活動消息\n時間\n聚會名稱\n負責人/講員或內容\n參與者\n地點\n4月9日(日)\n14:00pm\n衛蘭團契\n衛青團契\n查經會-耶利米哀歌\n龐君華牧師\n會   友\n副堂二樓\n4月11日(二)\n19:30pm\n紅本門徒\n＃1.引言－權威\n龐君華牧師\n課程參與者\n副堂二樓\n4月13日(四)\n19:30pm\n逾越節崇拜\nMYF青年\n會   友\n副堂二樓\n4月14日(五)\n19:30pm\n受難日崇拜\n被遺忘的苦難\n龐君華牧師 台北聖樂團\n開    放\n城中牧區\n4月15日(六)\n12:00pm\n姊妹會\n戰勝試探\n陳馥蓮姊妹\n姊妹們\n陽明山福音園\n4月15日(六)\n14:00pm\n衛青團契\n職場人際關係\n魏懋文姊妹\n開    放\n副堂二樓\n4月16日(日)\n7:00am\n10:00am\n復活節\n朝陽崇拜\n早午堂聯合崇拜\n龐君華牧師\n會     友\n戶外中庭\n城中牧區\n4月16日(日)\n14:00pm\n衛蘭團契\n同工會\n同工們\n副堂二樓\n4月17日(二)\n19:30pm\n紅本門徒\n＃2.創造的上帝－奇蹟\n龐君華牧師\n課程參與者\n副堂二樓\n4月20日(四)\n19:30pm\n堂會學校\n讀書會之帶領\n黃于庭姊妹\n課程參與者\n副堂二樓\n4月23日(日)\n14:00pm\n衛蘭團契\n衛青團契\n信仰專題\n衛斯理教你怎樣蒙恩得救-\n進入世界\n龐君華牧師\n會   友\n副堂二樓\n4月25日(二)\n19:30pm\n紅本門徒\n＃3.悖逆的人－罪\n龐君華牧師\n課程參與者\n副堂二樓\n4月27日(四)\n19:30pm\n堂會學校\n信仰分享課程\n龐君華牧師\n課程參與者\n副堂二樓\n4月28日(五)\n19:30pm\n月禱會\n龐君華牧師\n會    友\n城中牧區\n4月30日(日)\n14:00pm\n衛蘭團契\n讀書會\n會   友\n副堂二樓\n5月2日(二)\n19:30pm\n紅本門徒\n＃4.蒙召的子民－約\n龐君華牧師\n課程參與者\n副堂二樓\n5月4日(四)\n19:30pm\n堂會學校\n關懷佈道課程(1)\n龐君華牧師\n課程參與者\n副堂二樓\n\u0001\n本週每日經課\n以下內容亦刋載於http://wf.fhl.net/daily/old.html\n＊建議會友可於早晨（或午前）、下午（或黃昏）以及睡前，分別預留出讀經及默想的時間，能養成作筆記的習慣則更佳；福音書可於上午（或午前）或睡前閱讀。當然如果你有大段的充裕時間，亦可三段經文一次閱讀及默想。此外，請以祈禱作為開始與結束，有些默想的問題可以存在心裡，在一天當中或當你靜下來時反覆的思量。每日有規律的讀經靈修，使我們的心靈習於聆聽上主的心意，生活依循上主的方向。＊＊\n除了聖經的閱讀外，請每天撥出一段代禱的時間，請參考週報所記的代禱事項欄，為世界及我們所在的社會、社群及教會代禱，代禱前請先閱讀代禱事項，用你的心靈去想像代禱對象或事件的情況，按著你的感動為這些事代禱，自問可以作些什麼？日後也留心這些事情的發展，留心上主的工作。\n4/10\n禮拜一\n哀1:1-2、6-12\n林後1:1-7\n可11:12-25\n哀歌的卷名原文有「為何」的意思，為何會有現在這種景象呢？為何會是我（們）呢？這是面對苦難的第一個反應，我們會很自然地回想以前的光景，在「那個時候」誰會想到有今天呢？但是仔細想想，真的完全沒有徵兆麼？在我們受苦以前，真的完全沒有任何線索麼？\n多受基督的苦楚，就靠基督多得安慰，並且可以去安慰「那遭受各樣患難的人」，這是保羅對苦難的態度。受基督的苦楚意思是為基督而受苦，或作受苦是為基督所受的；得基督的安慰，是可以使人忍受各樣的苦難。請認真地想想你正在何事上正在或曾經為基督而受苦？你可體驗祂的安慰？\n無花果樹、聖殿、祈禱都是猶太人重要的民族與信仰生活的象徵。無花果樹是以色列平安的隱喻，它應該結果但是卻沒有結出果子來；聖殿應該單純的敬拜上主，如今成了做生意的地方；祈禱是人內心對上主的敬拜與交託，現在反而成為抬高自己的手段，大家只重形式，而不重與上主關係的實際。請想想看我們現在的教會生活是不是有這樣的危險呢？\n4/11\n禮拜二\n哀1:17-22\n林後1:8-22\n可11:27-33\n上主是公義的，但我現在卻是在受苦，這樣的想法使我們感到困惑；然而我們可曾想過會不會正因為上主是公義的，所以我們必須要接受這個苦果？\n上主的盼望或應許，在保羅看來是十分確定的，毫不含糊，聖靈就是保證；所以保羅在瀕臨生死的患難中，也不失去指望。請回想你曾遇見過的最大苦難，你可有失去指望？\n有些權柄是不用加以解釋的，問耶穌的權柄從那裡來的文士們，心裡已感覺到祂所行的是來自特殊的權柄，耶穌不願在此時讓他們找到把柄，所以不直接回答他們。其實在教會中有些權柄往往不是來自地位、職分等等，往往由愛所建立的權柄更有影響力，你在你服事的領域中可有這樣的權柄？\n4/12\n禮拜三\n哀2:1-9\n林後1:23-2:11\n可12:1-11\n更令人費解的是，上主竟然允許祂的聖殿被玷污，祂的聖城受到毀壞。百姓以為只要有這兩樣在，我們只要住在有聖殿的聖城中，應該不會受到任何的災難。然而上主不是受人間的建築所左右的主，祂的行事是以祂的公義與慈愛為依歸。自恃有聖殿，而不顧到上主的公義，上主不能讓祂的百姓有這樣的誤解，以為祂只是坐在聖殿中的上主。\n保羅十分細心地安排自己的探訪，在前一封信中，他對這個教會有所責備，但又關心他們是否因此憂愁，所以這封信流露了牧者的心腸，只有教會裡（被他責備的人）的人，是唯一使他快樂的，所以他一定要確定他們沒有因他的責備而仍在憂愁，這是一種在愛中的責備，常是牧者心情的矛盾，因為有愛才會責備，也因為愛而不忍。上主的心腸不也是如此麼？\n耶穌再次說明自己受難的意義，祂受難並非失敗，而是上主的旨意要挽回悖逆的人；此外，也凸顯出人的悖逆的程度，連上主的兒子都要害之。受難週，讓我們一方面思想上主的愛，也思想人的惡，這是造成基督受難的原因。\n4/13\n禮拜四(逾越節)\n哀2:10-18\n林前10:14-17、11:27-32\n可14:12-25\n在傷痕中我們好像忘記了什麼是健康的情形，也不可能想像日後還有可能復原；所以會覺得如何才有可能被安慰呢？如何才能被醫治呢？此外，為何仇敵會誇口，他們誇口什麼？上主如何看待呢？\n領受基督的血，就是分擔祂的苦難，領受基督的身體，就是學習祂的捨己，最後我們是同飲於一杯，同受一個餅，意思是我們的生命因此而相互連結，普世教會與歷代教會在領受了聖餐後，我們的關係就因基督而連結，成為祂的肢體，繼續祂在這世上的任務。\n耶穌與門徒的最後晚餐，雖是最後卻也是開始，開始了上主新一階段的序曲，往後教會未間歇地舉行同樣的聖餐，表示在基督裡的連結，也表示繼續基督的任務，更表示願意等候，等候那日子來到，我們要與主真正的共進那永恆的晚宴。\n4/14\n禮拜五(受難節)\n哀3:1-9、19-33\n彼前1:10-20\n約13:36-38\n來到了承受苦難的第二部曲，終於可以接納苦難這個事實，也開始企盼平安，於是開始尋求上主，開始等候祂的作為，憂悶中開始感覺有指望。你有這樣從不斷問「為何？」到接納，並且尋求意義與指望將來的經歷麼？你如何幫助受苦中的人，讓他們記憶起健康、太平時的生活，也激起他們的盼望？\n基督的苦難與後來的榮耀，都是上主的計畫，特別是經過苦難而得的榮耀，所以我們也當受苦，我們要在我們的自由中選擇接受束縛，我們不能讓我們的私慾毫無限制地發展，也不能再蒙昧無知；反之，我們要聖潔，敬畏地生活。在受難日的今天，你可曾決心要被束縛麼？\n「主往那裡去？」這不是普通的問題，雖然主回答我們將來也要跟祂去，但是我們還是暫時要與主分離，因為我們還有在世上的任務，在世上的操練，這些都是預備，預備好我們可以到主的榮耀中。所以在世上的點點滴滴都是功課與預備，你正在學習什麼功課？認真地問，你真的嚮往主所在之地麼？還是你蠻留戀現在之地？\n4/15\n禮拜六\n哀3:37-58\n來4:1-16\n羅8:1-11\n書中的作者開始「深深地考察自己的行為」，這表示他開始在找尋苦難之於他的意義；在求告中也聽到「不要懼怕」的安慰與指引。苦難逼得人非要面對上主不可，真真實實地依賴祂的安慰。懼怕苦難比實然地承受苦難更叫人難受，懼怕會使我們失去生存的勇氣。相反的在信心中勇於承受苦難，往往令人不以為苦。周圍有什麼事令你感到懼怕麼？\n這裡說要我們畏懼地生活，又說我們應當坦然無懼；其實這是要我們知道何所懼？我們當敬畏上主地生活，我們當無懼於挑戰；我們當怕什麼？不怕什麼？你可分清楚了麼？\n身體雖因罪而死，心靈卻因義而活。死的是我們帶罪的部份，活的是我們信心所帶來的義的部份。在你的生活那些部份一直衰退？那些部份一直更新？\n4/16\n禮拜天\n徒10：34-43\n詩118：1-2, 14-24\n林前15：1-11\n約20：1-18\n復活主日\n讀經推廣活動 牧區基督教教育委員會\n宗旨：\n為鼓勵會友養成有紀律的讀經習慣，從每日經課獲益，特舉辦此讀經活動。\n讀經範圍：\n以今年教會每日經課四月至九月之內容為主。\n（包含舊约,新约書信,褔音書三部份）\n辦法：\n於今年九月下旬教會退修會中，舉辦讀經遊戲有獎活動，以趣味的方式推廣讀經。\n於今年退修會之前，徵求會友讀每日經課之心得分享（每篇字數約伍佰字左右，篇數不限），將於退修會中供與會者閱讀，並於今年底前，將會友之讀經心得彙编成册。\n大齋期第五主日\n主後二OO六年四月二日\n證道主題：落在地裡的麥子\n經課：耶利米書31：31~34、希伯來書5：5~10、約翰福音12：20~33\n證道：龐君華牧師    整理:楊秀惠姊妹\n前言\n今天是大齋期的第五個主日，大齋期已近尾聲，下個禮拜就要進入一個更高的高潮，就是棕樹主日，也就是進入聖週，耶穌復活之前重要的一週。\n在這幾個禮拜中我們不斷地思考，如何從不同的角度去認識耶穌，過去的經課裡提到耶穌就好像新的聖殿，祂是真正救贖的中心，同時也提到耶穌是上帝的力量－智慧。上禮拜我們更提到耶穌就好像舊約裡被舉起銅蛇，使仰望祂的人可以得救，在痛苦中仰望被舉起的銅蛇，就好仰望基督一樣可以得到救贖，但這一切是怎麼發生的呢？為什麼仰望基督可以得到救贖呢？這一切過程與今天的經文有非常密切的關係。\n受苦的時候到了\n今天福音書經課裡面講到一群人，這群人是希臘人，可見是外邦人，他們來找腓力，腓力的名字本身就暗示他也有希臘血統。他們要來見耶穌，耶穌在這時候講了一段話，祂說：「時候到了。」也就是將要來臨的時間已經滿足了，而且上帝光榮的日子來到了。我們發現在新約裡面，每次耶穌說「時候到了」的時候都是跟他的受苦有關。\n「榮耀與受苦」是一體兩面的，是一曲雙重奏的樂章，在裡面是彼此互相輝映的。耶穌對這門徒說：「一粒麥子不落在地裡，就不能結出許多子粒來。」一粒麥子必須落在地裡死了，才能結出許多子粒來。\n從自然界來觀察必須經過一番掙扎，必須經過一番代價，果實才會結果。在不同文化裡有不同的諺語，在我們中文古書裡面有一句提到「不經一番寒澈骨，哪得梅花撲鼻香。」如果不經過一個寒冬，梅花如何在寒冬中綻放花朵呢？在台灣諺語中也講到「落土不凋雨夜花」也就是說花落在土地裡，雖然是凋落了，仍然堅持它的生命，這句話被一位作者用作描寫二二八事件中，奮勇抵抗的女英雄謝雪紅女士。\n但是今天耶穌講到的例子跟這兩個諺語是不一樣，祂講的不是經過一番寒冬，就會長出新的花蕊來；或是一種精神的存在，雖然生命完結但是卻在精神上不朽。\n祂講的是一個實實在在的生命，必須要經歷死亡，經過生命的消亡，毫無抵抗的，面對這些黑暗，然後才能結出新的果實，新的生命是經歷死亡而產生的。這段經文非常重要，但願我們一直到復活節，都不斷地去思想，經歷死亡才能得到榮耀，這是耶穌的生命及使命的一個重要寫照，是了解耶穌的重要角度。\n耶穌所說的死亡，不是一個結束，也不是一個段落，是生命真正的開始，祂要求跟隨祂的人，或者跟隨祂信仰的群體，都要一同來走這條路。代表苦難、死亡和光榮的就是我們的十字架，許多人把十字架作為一個裝飾，不論是認不認識基督教的人都會掛著十字架作為裝飾，也許他並不明白佩帶十字架的意義。\n記得曾經參訪過一些教會，因為某種原因，他們不能把十字架掛在教堂外面。在伊斯蘭信仰政府所統治的地區，往往申請教會用地是受到很大的限制，所以有些時候為了不刺激當地的政府，所以在教堂的建築外不敢把十字架掛在外面。所以有實在外表看不出來這是教會，因為外面沒有掛十字架。但這不要緊，因為只要裡面有十字架就好。不只是在聖堂裡面有十字架，更重要的是在心中要有十字架；十字架不是一個裝飾，更不是一個形式上的佩帶作基督徒的標誌。十字架的要求是要我們付出更多的代價，而且要更加的儆醒。\n十字架象徵受苦，但受苦有不同的意義。有的人為自己的成功付出代價，例如要有很好的琴藝，要有很好的某種成就，則必須先吃苦，這苦是為了自己的前程或成就。受苦有另外一個層次，是為我們自己的罪，罪會使人受苦，而且即使是基督徒有時也會為罪的控訴而受苦，因為他內心有掙扎。保羅寫道：「我心裡不願意的，我反倒去做；我願意做的，反而做不到。」因為罪在他心裡使他掙扎及受苦。受苦也有自找的，自己決定錯誤，做錯了事情，以致於受苦。\n但是受苦也有一種是無辜的，我們什麼都沒做，結果卻受苦了。在牧養關顧上常常會遇到這樣事情，有些人遇到一些困難，會問：「牧師啊！為何是我？為什麼會這樣？為什麼我已經是基督徒，信主多年，可是為什麼會有這樣的事臨到我？」假如我能整理出一個避免受苦的教戰法則，我真的很願意公開，讓我們大家都可以不會受苦，但這情況是人生中很難預料的。\n另外有一種受苦也就是基督的精神，就是為他人而受苦，祂在承擔別人軟弱的時候而受苦。祂受苦不是因為自己的成就，自己的罪，自己的無知，也不是因為各種無端端的苦難，而是有意識的要承擔人類的困難，所託付給祂的使命，就是為他人而付出代價，因此必須要受苦。\n所以耶穌要求人，要真正的懂得放下生命，真正放下生命願意預備好，各種情況都要準備接受，這樣的人反而得到生命。如果一個人的生命狀態是，有許多不能觸碰的，則生命反而是受到限制。我們常常必須要經過受苦，才能認出我們的信仰。\n背負與犧牲─基督徒的記號\n曾經看過一個紀錄，在十六世紀時，外國有一個宣教士到大陸一個偏遠的地方，宣教士很認真的在村裡工作，他傳教，教導讀經，幫他們做事，村裡一部份人接受這信仰。宣教士主持禮拜，大家一起崇拜，平常也探訪他們，牧養他們。可是不久這宣教士過世，那麼偏遠地方一時沒有人過去，過很久這差會也派不出人過去，在山裡的基督徒就想怎麼辦呢？在山裡面有一半的人不知道什麼是基督徒，以前有宣教士在，只要找他就可以說明「這是一位基督徒」。\n可是現在這些信徒，不知要如何向別人解釋他們是什麼人？如何向別人介紹自己的信仰呢？以前介紹信仰是宣教士負責的任務，現在宣教士離他們而去，他們應該如何進行呢？於是這群人坐在一起想，用什麼方式來顯現信仰的基督。有一個婦人就提出一個方法，我們怎麼講都沒有這宣教士講的好，在這山裡梯田耕種，每天都要挑水去灌溉，不如我們挑水經過的地方，自己澆水灌溉也幫別人澆水灌溉。剛開始村裡的人覺得這些人很奇怪，怎麼幫他們灌溉田地呢？覺得是一時想做好事。日子過久，發現仍是一直挑水繼續幫他們灌溉，如此一個季節一個季節地過去，這群人還是繼續不斷的先灌溉他們的田，再灌溉自己的田，尤其是幫助那些沒有能力灌溉的人稻田。久而久之，村子裡面的人就叫這些人去挑水，他們不知道什麼叫基督徒，只是知道這群人是挑水的人，為什麼？因為他們肯背負，肯付出代價，受苦成了他們的記號。如果我們要表明我們的信仰，要用教義去解釋什麼是光榮、榮耀，可能講得人家都聽不清楚，但是迫於親身經歷時，就能敢勇於為他人而受苦這是基督徒真正的意義。\n整本聖經，都講到信徒們付出代價，上帝的計畫就一步步的展開。有一首英文詩，翻譯如下：「如果摩西，不過紅海摩西走到紅海邊一看，唉呀糟糕！這麼大的海，則不去了；如果挪亞不建方舟，挪亞說：建方舟工程好累呦！不如不要做好了；如果耶利米不流眼淚，耶利米被稱為含著眼淚的先知；如果阿摩司繼續種田不去宣講，阿摩司本是種田的，修理桑樹的，上主要他去宣講上帝的道，他說我怎麼可能，可是他還是去了；如果路得不去照顧他的婆婆，路得說反正先生死了，你回你家，我回我家；如果大衛不去面對歌利亞；如果馬利亞拒絕上帝使者給她的呼召，懷孕生子；如果施洗約翰說我不要到曠野去，曠野太苦了，寧可到大的講堂去講道；如果彼得沒有離開加利利；如果保羅偷懶，不寫信；如果耶穌不上十字架，那會是怎樣的情景呢？」所以你看到整個聖經，其實是在舖展一群一群的聖徒，他們不斷地付出代價，讓上帝的旨意可以實現。在付代價的過程中去明白什麼是上帝的道，這變成我們近代常常會忘記的訊息。\n大齋期給我們重要的提醒，有一位神學家Richard Niebuhr說：現代教會不管那個宗派都有一種危險，這危險是他們想傳一個不會發脾氣的上帝，帶領著一群沒有罪疚的子民，要求他們進一個無須審判的天國，然後宣傳一個沒有十字架的基督；這是基督宗教失去身分的危險。面對現代的挑戰來傳福音時，糞望人家能接受信仰是因為信耶穌只要禱告，就可得到什麼；信耶穌只要來聚會，就會獲得祝福，佈道時開出很多的支票，不錯，這些上帝都能做到，但是真正的重點不在這裡，真正的重點在有沒有十字架，有沒有付代價，耶穌呼召人從來沒有隱藏祂的十字架，只有經過十架，才會有生命的果實。\n真實的苦難\n今天我們提到這種苦難，耶穌預備要受苦，是個真真實實的苦難，耶穌感到極其憂傷，就好像約翰福音及其他的福音書中記載，耶穌極其憂傷，祂感到這種苦難在祂面前是那樣的真實，祂必須如此沉重的背負，所以祂說如果可以選擇的話，寧可不以這種受苦的方式，因為人性的一面都希望趨吉避苦，但是看到正是人性的救贖需要付出與受苦，所以耶穌極其憂傷，而且感到真真實實的痛苦，不是演戲。\n最近有一齣歌劇－「鐘樓怪人」，男主角唱得非常的好，大家都覺得他非常的特別，他能彎著腰唱歌，卻能找到其聲音的共鳴點，能夠從頭到尾都弓著背在演唱。當謝幕時大家看到該主角不是駝背的，而是長得很高的演員，他不過是在「飾演」一位駝子罷了。可是基督的苦難是自己踏上苦難，不是演戲，是真真實實的，必須要承受且呼召跟隨祂的也要承受，因為唯有這樣，才能得的到生命，必須如此，我們有這樣的經歷，才能說我們是跟隨基督的，這段經文強調面向十字架，面對苦難，可是這要怎麼做呢？\n結語：受苦的預備\n約翰衛斯理有很好的教導，在他為班會制定的「行為的準則(Rules of Conduct)」時這樣的說：你要竭盡所有的方法，使用所有能用的工具，到你所能去的地方，在任何的時間，到任何的百姓當中，用你所能活的歲數，行所有的善事。這與盡心、盡性、盡力愛上帝，是異曲同工的教導，他要求我們竭盡所能去行善，在這過程中一定會遇到挫折，一定會遇到險阻，一定有人不認同，一定會遇到所不想遇到的，但是耶穌說祂的時候到了，那是光榮的日子，也就是受苦的日子，如果我們真的要了解復活節或是受難週信仰真正的意義，唯有對生命有這樣的準備，預備好放下，也預備得著。\n今天是聖餐的主日，在舊的法規裡的聖餐禮文第一式中提到，在為餅酒祝聖的時候，其中有一句經文說「我們同領一杯分擔基督的苦難」，所以今天我們領受聖餐時好好想一想這句話，我們不是只是一個宗教形式，我們不是例行每個月形式地完成我們聖餐的禮。今天我們立志在主的面前說「主啊！我願意分擔祢的苦難，願祢把心胸為我敞開。」\n\u0001\n大齋期第五主日\n2006.04.02\n各項聚會出席人數表\n早堂主日崇拜\n64人\n午堂主日崇拜\n20人\n兒童主日學\n15人\n堂會學校\n10人\n衛蘭團契\n21人\n衛少團契\n8人\n大齋期第五主日\n2006.04.02\n奉獻明細表\n早堂崇拜\n4,310元\n月捐\nB006\n35,000元\nB007\n10,000元\nB012\n3,500元\nB016\n1,000元\nB018\n3,200元\nB022\n6,000元\nB032\n4,300元\nB036\n15,000元\nB052\n3,500元\n仁愛捐\n3,870元\n特別奉獻\n仁愛捐\nB036                       1,000元\n衛理神學生培育計畫\nB036                       1,000元\n獻花奉獻\nB008                        500元\n主日學奉獻\n105元\n合計\n92,285元\n復活主日\n2006.04.16\n服事人員表\n講員：\n龐君華牧師\n司會：\n蔡本源弟兄\n司琴：\n李佳鴻弟兄\n讀經：\n劉博樺弟兄\n會前領唱：\n黃玲媛姊妹\n奉獻詩：\n聯 164\n「信靠順服」\n林永吉弟兄\n路進弟兄\n兒童主日學：\n楊肇悅姊妹\n蔡孟庭姊妹\n司獻：\n焦瑬弟兄\n鄭漢生姊妹\n獻花：\n黃運湘弟兄\n獻刊：\n胡瑠美姊妹\n講章整理：\n楊秀惠姊妹\n獻詩：\n城中牧區詩班\n城中幼稚園\n愛宴：\n城中幼稚園\n愛宴庶務：\n弟兄姊妹\n衛理公會城中牧區的呼召\n就是在基督的愛中回應上主的福音，我們透過崇拜、\n學習與關顧、服務、傳揚福音來活出基督門徒的身分。\n城中牧區（2006年4月09日–2006年4月16日）聚會時間與內容\n時間\n聚會名稱\n聚會內容\n講員\n地點\n日\n10：00~11：00\n主日崇拜\n棕樹主日\n龐君華牧師\n會　　堂\n12：30~13：40\n午堂崇拜\n棕樹主日\n龐君華牧師\n會    堂\n14：00~15：30\n衛蘭團契\n查經會-\n耶利米哀歌\n龐君華牧師\n副堂二樓\n四\n19：30-21：00\n崇拜\n逾越節晚餐崇拜\n龐君華牧師\n副堂二樓\n六\n14：00-16：30\nMYF 青少年團契\n作文班\n拜訪神秘家庭\n黃于庭姊妹\n張心怡姊妹\n副堂二樓\n下\n週\n日\n07：00~08：00\n朝陽崇拜\n朝陽崇拜\n龐君華牧師\n中庭\n09：00~09：45\n詩班獻詩\n詩歌練唱:祂復活降臨\n我心中仰望十字寶架\n會　　堂\n09：45~10：00\n會前領唱\n聯合詩選88、91、89\n黃玲媛姊妹\n會　　堂\n10：00~11：00\n早午堂主日崇拜\n復活主日\n龐君華牧師\n會　　堂\n10：00~11：00\n兒童主日學\n兒童主日學\n楊肇悅姊妹\n蔡孟庭姊妹\n副堂二樓\n14：00~15：30\n衛蘭團契\n同工會\n同工們\n副堂二樓\n復活主日\n使徒行傳 10：34～43　  詩篇118：1～2、14～24\n哥林多前書15：1～11\t    約翰福音20：1～18", "nchars": 15145, "source_file": "周報/2006/06-04-09wf主日程序.doc", "ext": ".doc"}