{"date": "2018-05-13", "service": "主日崇拜", "season": "復活期第七主日", "date_text": "主後二○一八（民107）年五月十三日", "color": "白", "preacher": "龐君華牧師", "presider": "龐君華牧師", "sermon_title": "僑居世上的群體", "roles": {"主禮": "龐君華牧師", "證道": "龐君華牧師", "司會": "林盈君姊妹", "讀經": "簡大鈞弟兄", "司琴": "陳芝英姊妹", "司獻": "李菊英姊妹、楊秀惠姊妹", "領唱": "林盈君姊妹", "獻花": "何建弟兄", "獻刊": "陳暄姊妹", "招待": "楊秀惠姊妹", "獻詩": "衛家團契", "兒童主日學": "徐珮寧姊妹\n王怡文姊妹\n陳芝英姊妹"}, "scriptures": ["使徒行傳1:15-17, 21-26", "約翰壹書5:9-13", "約翰福音17:6-19"], "hymns": [{"book": "新普頌", "no": "297", "title": "基督凱旋"}, {"book": "新普頌", "no": "293", "title": "榮登寶座"}, {"book": "新普頌", "no": "507", "title": "為教會合一禱告"}, {"book": "新普天頌讚", "no": "884", "title": ""}], "full_text": "復活期第七主日\n主後二○一八（民107）年五月十三日上午十時正\n白色象徵純潔、喜樂和真理的光輝，用於與主基督直接有關的節期，如聖誕期、復活期、顯現日、\n升天日、聖三一主日、基督登山變容主日。\n***崇拜進行時，請暫時關閉您身上的行動電話及呼叫器***\n入殿禮\n詩歌領唱  ………………………………………….……….………林盈君姊妹\n默想音樂  ……………………………………….…………………… 會眾肅靜\nBach Cantatas BWV 6 2. Alto Aria : HochgelobterGottessohn3:09HochgelobterGottessohn,Laßesdirnicht sein entgegen,\nDasswiritztvordeinemThronEineBitteniederlegen:Bleib, ach bleibeunser Licht,Weil die Finsterniseinbricht.\n高高榮耀神兒子，你不要拒絕我們。我們在你寶座前，擺上我們的請求：留下來光照我們，因為黑夜已來到。\n（姚振銘弟兄提供）\n序        樂  ………………………………………………..…………………司琴\n安  靜  頌  …【「主在聖殿中」《新普天頌讚》784首】……… 眾(坐)肅靜\n主在聖殿中，主在聖殿中，普天下的人，\n在主面前，都應當肅靜，肅靜，肅靜，應當肅靜。阿們。\n宣        召  ………………………………………………………..…………司會\n加利利人哪，為甚麼站在這裏望著天空呢？這位離開你們、被接升天的耶穌，你們看見他怎樣升天，他也要怎樣回來。\n（使徒行傳1:11現代中文譯本）\n頌        讚  …新普頌第297首「基督凱旋」……..……….…領唱╱眾立同頌\n(第1、4節齊唱，第2節女生，第3節男生)\n始  禮  文\n啟：你們要擊掌，要高聲歌唱；\n應：上主是可敬的，升起的君王是可畏的！\n啟：百姓在祂腳下，萬國在地上顯得渺小，\n應：祂已揀選了祂的百姓，祂已設定了祂的寶座，\n啟：那高昇的是那曾經降臨的，那怎樣升起的也要怎樣再臨；\n應：讚美在榮耀中高高升起的主，等候在榮耀中再臨的主！\n祈        禱  ………………………\t……………………………………司會/眾立\n主  禱  文  …【「主禱文」《普天頌讚》649首】……………………司會/眾立\n我們在天上的父，願人都尊父的名為聖。\n願父的國降臨。願父的旨意，行在地上，如同行在天上。\n我們日用的飲食，求父今日賜給我們。\n又求饒恕我們的罪，如同我們饒恕得罪我們的人。\n不叫我們遇見試探，拯救我們脫離兇惡。\n因為國度，權柄，榮耀全是父的直到永遠。阿們。\n詩        歌  …新普頌293首「榮登寶座」…………..……………… 司會/眾坐\n(第1-2節→間奏→第3-4節)\n聖道禮\n祈光禱文 ………………………..………………………………………… 全體\n啟：我們一同求主賜下亮光！\n合：復活的基督，當祢完成世上的任務，光榮高升時，願聖靈臨到屬祢的群體，並以祢的話語引導我們，行在祢的路上，直到祢再臨的時刻。榮耀歸與父上帝。阿們。\n讀        經  ………………………………………….…………..……簡大鈞弟兄\n經  課  一  使徒行傳1:15-17, 21-26     (新約179頁)\n啟  應  文  詩1  ……………………………………….…………..…… 眾坐同應\n啟：不從惡人的計謀，不站罪人的道路，不坐傲慢人的座位，惟喜愛耶和華的律法，晝夜思想他的律法；這人便為有福！\n應：他要像一棵樹栽在溪水旁，按時候結果子，葉子也不枯乾。凡他所做的盡都順利。\n啟：惡人並不是這樣，卻像糠粃被風吹散。\n應：因此，當審判的時候惡人必站立不住，罪人在義人的會眾中也是如此。\n合：因為耶和華知道義人的道路，惡人的道路卻必滅亡。\n榮  耀  頌  …………………………………………….………….…………眾立\n「但願榮耀，歸於父、子、聖靈，父、子、聖靈。\n起初這樣，現在這樣，以後也這樣，永無窮盡。阿們阿們！」\n經  課  二  約翰壹書5:9-13    (新約387頁)\n啟：這是上主的道\n應：感謝上主\n獻        詩  願主賜福母親們………………………………………...…衛家團契\n願主賜福母親們，引領她們全路程，求賜智慧與恩光，白日黑夜都照亮，身為母親今求祢使我順服祢旨意，時常經歷祢同在，除我憂懼蒙主愛。我不願求更多福，只求忠於主託付，每日教導眾兒女，常常遵行主話語，願主平安與聖靈，充滿每顆母親心，但願他們享安康，樂在母職享安詳。\n福音前禱  【「你的話是我腳前的燈」《新普天頌讚》832首】…司會/眾立\n「你的話是我腳前的燈，是我路上的光。阿們。」\n司會（啟）：主耶穌基督的福音是記載在約翰福音17:6-19\n會眾（應）：願榮耀歸於主基督。\n福  音  書\t  約翰福音17:6-19        (新約169頁)……….…….……司會/會眾立\n司會（啟）：這是上主的福音。\n會眾（應）：願讚美歸與主基督。\n證        道  ....僑居世上的群體 ……………...…..…...…...………  龐君華牧師\n回  應  詩  …新普頌507首「為教會合一禱告」…………..……司會/會眾立\n(第1、4節齊唱→第2節男生→第3節女生)\n信仰告白  …使徒信經（參新普頌封面裏頁）………………………….眾立\n奉        獻  ……………………………………………………………….眾樂意\n司會：我們既然成為罪蒙赦免，與上帝和好的子民，讓我們把自己和禮物獻給上主。\n會眾：（奉獻後頌唱：「向主獻呈」）凡我向主所呈，都是主賜的恩，凡我所有，都屬於主，是主託付僕人。\n報        告  ……………………………………..…………...……..…………司會\n牧        禱  …………………………………………………..….……龐君華牧師\n差遣禮\n三  一  頌  ………………………………………..………..…….…………眾立\n普天之下萬國萬民，齊聲讚美父、子、聖靈。\n三位一體，同榮同尊，萬有之源，萬福之本。阿們。\n祝        福  …………………………...……..……….….…..………龐君華牧師\n賞賜平安的上帝，已經使我們的主耶穌，就是那群羊的大牧人，從死裡復活；也使你們在各樣善工上，完全遵行他的旨意。又願全能的上帝，聖父、聖子、聖靈，賜福給你們，直到永遠，阿們。\n阿  們  頌  …………（新普天頌讚884首）………..……...….…………眾立\n退  殿  曲  天庭歌頌上主（泰澤詩選）……….…………………… 眾立同頌\n天庭歌頌上主，大地讚美上主；基督耶穌祂已真復活。\n天庭歌頌上主，大地讚美上主；基督耶穌祂已真復活。\n*退殿曲結束後，彼此問安*\n報告事項\n歡迎今天第一次參與我們崇拜的朋友，我們期待有機會多認識您們，也邀請您會後與我們一起享用午餐愛筵。\n今天是母親節，牧區準備一點小禮物，送給母親們，祝母親們母親節快樂。\n本週五（5/18）晚七時，舉行本月份的泰澤合一祈禱，歡迎弟兄姊妹參與。\n五月份是年度報稅的時間，弟兄姊妹應已收到紙本奉獻收據，若尚未收到或有疑問請洽李幸真姊妹。\n每禮拜五晚的「認識基督信仰」班，五月25日開始新的一季的課程，共讀魯益師（C.S.Lewis）的名著《返璞歸真》（Mere Christianity），歡迎有心探討信仰的會友參與或推薦慕道友參加（參第7頁，可向林盈君姊妹購書）。\n牧區報告：有意進一步認識信仰的朋友，請洽牧師或留言在留名卡。有意要於復活節領洗、轉入會籍或補辦會友證的會友請洽牧師。\n為我們所在的土地與社會及世界守望\n為我們所居住的土地\n為現代社會中的母親們祈禱。\n為我們所在社會真正和諧祈禱，無論族群、省籍、世代、職業間彼此包容接納。也為公義制度建立，包括司法、金融、經濟、土地等的公平正義代禱。\n為在安養院中的身障人士，以及需要長期照顧的長者們和他們的家庭代禱。\n請為社會中承擔工作與家庭責任的青年夫婦們祈禱。也為考試季節的學生們代禱。\n為待業中的人士，及家庭代禱。\n今年有選舉，目前社為的氣氛正逐漸升溫，請為選舉的過程中，社會的和諧，公平清潔的選舉過程代禱。\n為我們的牧區\n為牧區繼續50週年堂慶後的目標「成為真實的門徒群體」，以及總會未來的目標朝向「徹底的門徒」等門徒概念的推廣與落實代禱。也為本堂今年的58週年，及總會今年65週年感恩。\n請為會友們的身心靈的健康代禱。並為牧區各小組集團契禱告，希望更多會友參與團契生活，一同學習「成為真實的門徒」。\n為會友們的身、心、靈健壯代禱，為生病住院、復健中的會友及家人祈禱。\n為牧區推動讀經的計畫，如靈修讀經、聖經史地、各查經班以及團契的查經，及安排中的門徒課程代禱。\n為普世教會\n為普世教會的合一，在世上作美好的見證。\n為兩岸緊張的緩和、世界的和平祈禱。也為東亞的情勢緩和感謝。\n為國與國之間在經濟、環保及糧食問題的合作祈禱。\n為各地因戰禍或自然災害而流離失所的難民們祈禱。\n為在不知名的暴力下受害的人們祈禱，為各地暴力、恐怖的消弭祈禱。\n聖經史地課堂\n為鼓勵會友研讀聖經，牧區自本月份起，每月第三主日下午13:00-15:00舉辦〈聖經史地課堂〉（第三週下午有活動，則順延到第四主日），介紹由聖經公會為聖經翻譯工作人員訓練的必讀教學影片，由牧師現場講解，歡迎弟兄姊妹參與討論。請會友及各團契鼓勵成員們參加。本課程共八次，上半年四次以舊約課題為主，時間如下：\n3/18聖經史地課堂01：\n聖經地理、氣候和農業\n4/22 聖經史地課堂02：\n從亞伯拉罕到約書亞\n5/27  聖經史地課堂03：\n從約書亞到希西家\n6/17 聖經史地課堂04：\n從希西家到希律\n禮拜五晚的認識信仰班VI 如此基督教\n時間：每週五晚7:30-9:00\n本季討論新書《返璞歸真》（Mere Christianity）\n作者：魯益士C. S. Lewis，出生於北愛爾蘭一個新教的家庭，自幼年母喪後對信仰感到質疑，年青時一度為無神論者。一次大戰期間從牛津輟學自願從軍，經歷了戰壕中的恐懼與無助。戰後返牛津完成大學，並留校擔任研究員。期間遇到著名作家，也就是《魔戒》的作者托爾金（J.R.R. Tolkien, 1892-1973）。在他的開導，及認真的反省下，重回基督信仰。\n由於他有如此信仰歷程，使他在介紹基督信仰時，更正視信仰的核心，深入的反省，與辯解。本書是二戰期間魯益士在英國廣播電台一系列的廣播稿集結而成，不同於一般艱澀的神學著作；清晰地針對信仰的核心課題，與聽眾坦坦而談，很適合我們透過閱讀一起經歷他的思路歷程。魯益士終身為牛津大學文藝復興文學講座教授，其著作等身，其中膾炙人口的著作有《納尼亞傳奇》、《地獄來鴻》、《裸顏》以及兩本涉及痛苦與苦難的書《痛苦的奧秘》、《卿卿如晤》，前者寫於喪妻前，後者寫於喪妻後，充滿了感情與思辯的糾結，非常值得細細品讀。\n城中人的團契生活\n我們的聚會\n主日崇拜\t\t上午 10:00-11:30\n靈修分享小組\t禮拜一下午 7:30-9:30\n午間查經班\t\t禮拜四 1:30-4:30\n認識信仰班\t\t禮拜五下午 7:30-9:30\n姊妹會\t\t\t每月第二個禮拜六下午2:00-4:00\n衛智團契\t\t每月第二個禮拜二上午10:00\n衛家團契\t\t禮拜日下午12:00-2:30\n社青小組\t\t禮拜日下午 12:30-2:00\n詩班\t\t\t主日上午9:20-9:50，下午1:30-2:30\n學生團契\t\t禮拜六下午6:00（聚餐）7:30 （團聚）\n青年團契\t\t\t禮拜日下午12:30\n泰澤祈禱\t\t每月第三個禮拜五晚7:00-9:00\n泰澤祈禱\n乙年(第24週)每日經課\n復活期第六主日\n20180506\n各項聚會出席人數表\n聖靈降臨節（衛斯理主日）\n20180520\n早堂服事人員表\n復活期第六主日\n20180506\n奉獻明細表\n衛理公會城中牧區的呼召\n就是在基督的愛中回應上主的福音，我們透過崇拜、\n學習與關顧、服務、傳揚福音來活出基督門徒的身分。\n內尋靈性深度 外展生活服務\n城中牧區（2018年5月6日–2018年5月13日）聚會時間與內容\n聖靈降臨節／衛斯理主日\n徒2:1-21                        羅8:22-27\n詩104:24-34, 35b\t\t約15:26-27; 16:4b-15", "nchars": 4998, "source_file": "周報/2018/18-05-13主日崇拜程序5e.docx", "ext": ".docx"}